taior/__init__.py
taior/client.py
taior/crypto.py
taior/network.py
taior/node.py
taior/server.py
taior-1.1.0.dist-info/METADATA
taior-1.1.0.dist-info/WHEEL
taior-1.1.0.dist-info/top_level.txt
taior-1.1.0.dist-info/RECORD
