Metadata-Version: 2.1
Name: taior
Version: 1.1.0
Summary: The Amnesic Incognito Oblivious Routing
Home-page: https://github.com/taiorproject/taior
Author: Taior Project
Author-email: livrasand@outlook.com
Classifier: Programming Language :: Python :: 3
Classifier: License :: OSI Approved :: MIT License
Classifier: Operating System :: OS Independent
Requires-Python: >=3.6
Requires-Dist: cryptography
Requires-Dist: pycryptodome
